chariot_scaffold/__init__.py
chariot_scaffold/cli.py
chariot_scaffold/exceptions.py
chariot_scaffold/journal.py
chariot_scaffold/runtime.py
chariot_scaffold/tools.py
chariot_scaffold/api_server/__init__.py
chariot_scaffold/api_server/action_router.py
chariot_scaffold/api_server/app.py
chariot_scaffold/api_server/editor_router.py
chariot_scaffold/core/__init__.py
chariot_scaffold/core/base.py
chariot_scaffold/core/config.py
chariot_scaffold/core/plugin.py
chariot_scaffold/schema/__init__.py
chariot_scaffold/schema/alarm_model.py
chariot_scaffold/schema/base.py
chariot_scaffold/schema/config_model.py
chariot_scaffold/schema/indicator_model.py
chariot_scaffold-1.5.5.dist-info/METADATA
chariot_scaffold-1.5.5.dist-info/WHEEL
chariot_scaffold-1.5.5.dist-info/entry_points.txt
chariot_scaffold-1.5.5.dist-info/top_level.txt
chariot_scaffold-1.5.5.dist-info/RECORD
