Metadata-Version: 2.1
Name: chariot-scaffold
Version: 1.5.5
Summary: UNKNOWN
Home-page: UNKNOWN
Author: fengqing
License: MIT
Platform: UNKNOWN
Requires-Python: >=3.10
Requires-Dist: fastapi
Requires-Dist: uvicorn
Requires-Dist: requests
Requires-Dist: pyyaml
Requires-Dist: colorlog
Requires-Dist: python-multipart
Requires-Dist: pydantic
Requires-Dist: aiohttp
Requires-Dist: websocket-client
Requires-Dist: websockets
